lumapps/__init__.py
lumapps/cli.py
lumapps/client.py
lumapps/config.py
lumapps/utils.py
lumapps/helpers/__init__.py
lumapps/helpers/community.py
lumapps/helpers/enums.py
lumapps/helpers/exceptions.py
lumapps/helpers/group.py
lumapps/helpers/media.py
lumapps/helpers/user.py
lumapps/helpers/utils.py
lumapps_sdk_fork_poetry-0.2.2.dist-info/LICENSE.rst
lumapps_sdk_fork_poetry-0.2.2.dist-info/METADATA
lumapps_sdk_fork_poetry-0.2.2.dist-info/WHEEL
lumapps_sdk_fork_poetry-0.2.2.dist-info/entry_points.txt
lumapps_sdk_fork_poetry-0.2.2.dist-info/top_level.txt
lumapps_sdk_fork_poetry-0.2.2.dist-info/RECORD
