Metadata-Version: 2.1
Name: lumapps-sdk-fork-poetry
Version: 0.2.2
Summary: Lumapps SDK for Python
Home-page: https://github.com/lumapps/lumapps-sdk
Author: LumApps
License: MIT
Project-URL: Source, https://github.com/lumapps/lumapps-sdk
Project-URL: CI, https://circleci.com/gh/lumapps/lumapps-sdk
Project-URL: Documentation, https://lumapps.github.io/lumapps-sdk/
Project-URL: Issues, https://github.com/lumapps/lumapps-sdk/issues
Keywords: lumapps sdk
Platform: UNKNOWN
Classifier: License :: OSI Approved :: MIT License
Classifier: Development Status :: 4 - Beta
Classifier: Intended Audience :: Developers
Classifier: Programming Language :: Python :: 2.7
Classifier: Programming Language :: Python :: 3.6
Classifier: Programming Language :: Python :: 3.7
Requires-Python: >=2.7,!=3.0.*,!=3.1.*,!=3.2.*,!=3.3.*,!=3.4.*,!=3.5.*
Requires-Dist: requests (==2.20.1)
Requires-Dist: google-api-python-client (==1.7.7)
